PS C:\Users\Sakthivel\OneDrive\Desktop\JAVA_FSE> javap -c Decompile
Compiled from "Decompile.java"
public class Decompile {
  public Decompile();
    Code:
       0: aload_0
       1: invokespecial #1                  // Method java/lang/Object."<init>":()V
       4: return

  public static void greet(java.lang.String);
    Code:
       0: aload_0
       1: invokedynamic #7,  0              // InvokeDynamic #0:makeConcatWithConstants:(Ljava/lang/String;)Ljava/lang/String;
       6: astore_1
       7: getstatic     #11                 // Field java/lang/System.out:Ljava/io/PrintStream;
      10: aload_1
      11: invokevirtual #17                 // Method java/io/PrintStream.println:(Ljava/lang/String;)V
      14: return

  public static void main(java.lang.String[]);
    Code:
       0: ldc           #23                 // String Java
       2: invokestatic  #25                 // Method greet:(Ljava/lang/String;)V
       5: return
}
